pyduinocli/__init__.py
pyduinocli/commands/__init__.py
pyduinocli/commands/arduino.py
pyduinocli/commands/base.py
pyduinocli/commands/board.py
pyduinocli/commands/burn_bootloader.py
pyduinocli/commands/cache.py
pyduinocli/commands/compile.py
pyduinocli/commands/completion.py
pyduinocli/commands/config.py
pyduinocli/commands/core.py
pyduinocli/commands/daemon.py
pyduinocli/commands/debug.py
pyduinocli/commands/lib.py
pyduinocli/commands/monitor.py
pyduinocli/commands/outdated.py
pyduinocli/commands/sketch.py
pyduinocli/commands/update.py
pyduinocli/commands/upgrade.py
pyduinocli/commands/upload.py
pyduinocli/commands/version.py
pyduinocli/constants/__init__.py
pyduinocli/constants/commands.py
pyduinocli/constants/flags.py
pyduinocli/errors/__init__.py
pyduinocli/errors/arduinoerror.py
pyduinocli-0.35.0.dist-info/LICENSE
pyduinocli-0.35.0.dist-info/METADATA
pyduinocli-0.35.0.dist-info/WHEEL
pyduinocli-0.35.0.dist-info/top_level.txt
pyduinocli-0.35.0.dist-info/RECORD
