Metadata-Version: 2.1
Name: pyduinocli
Version: 0.35.0
Summary: Wrapper library around arduino-cli
Home-page: https://github.com/Renaud11232/pyduinocli
Author: Renaud Gaspard
Author-email: gaspardrenaud@hotmail.com
License: UNKNOWN
Platform: UNKNOWN
Classifier: Programming Language :: Python :: 2
Classifier: Programming Language :: Python :: 3
Classifier: License :: OSI Approved :: MIT License
Classifier: Operating System :: OS Independent
License-File: LICENSE
